jsonpyd/__init__.py
jsonpyd/cli.py
jsonpyd/jsonpyd.py
jsonpyd/util.py
jsonpyd-0.2.1.dist-info/LICENSE
jsonpyd-0.2.1.dist-info/METADATA
jsonpyd-0.2.1.dist-info/WHEEL
jsonpyd-0.2.1.dist-info/entry_points.txt
jsonpyd-0.2.1.dist-info/RECORD
