Metadata-Version: 2.1
Name: jsonpyd
Version: 0.2.1
Summary: Convert your JSON files into Pydantic classes.
Home-page: https://github.com/sinantan/jsonpyd
Author: sinantan
Author-email: sinantanwork@gmail.com
Requires-Python: >=3.8.10,<4.0.0
Classifier: Programming Language :: Python :: 3
Classifier: Programming Language :: Python :: 3.9
Classifier: Programming Language :: Python :: 3.10
Classifier: Programming Language :: Python :: 3.11
Requires-Dist: argparse (>=1.4.0,<2.0.0)
Requires-Dist: mypy (>=1.7.1,<2.0.0)
Requires-Dist: pydantic (>=2.0.3,<3.0.0)
Requires-Dist: pytest (>=7.4.0,<8.0.0)
Project-URL: Repository, https://github.com/sinantan/jsonpyd
